static_delivery/__init__.py
static_delivery/middleware.py
django_static_delivery-1.0.1.dist-info/LICENSE.rst
django_static_delivery-1.0.1.dist-info/METADATA
django_static_delivery-1.0.1.dist-info/WHEEL
django_static_delivery-1.0.1.dist-info/RECORD
