Metadata-Version: 2.3
Name: django-static-delivery
Version: 1.0.1
Summary: A middleware to delivery static files in Django.
License: MIT
Author: Stephan Jaekel
Author-email: steph@rdev.info
Requires-Python: >=3.10,<4
Classifier: Development Status :: 5 - Production/Stable
Classifier: Environment :: Web Environment
Classifier: Framework :: Django
Classifier: Intended Audience :: Developers
Classifier: License :: OSI Approved :: MIT License
Classifier: Operating System :: Unix
Classifier: Programming Language :: Python
Classifier: Programming Language :: Python :: 3
Classifier: Programming Language :: Python :: 3.10
Classifier: Programming Language :: Python :: 3.11
Classifier: Programming Language :: Python :: 3.12
Classifier: Programming Language :: Python :: 3.13
Provides-Extra: docs
Requires-Dist: Django (>=3.2)
Requires-Dist: Sphinx (>=3.5) ; extra == "docs"
Project-URL: Homepage, https://github.com/stephrdev/django-static-delivery
Project-URL: Repository, https://github.com/stephrdev/django-static-delivery
